dist
types_aiobotocore_accessanalyzer
types_aiobotocore_account
types_aiobotocore_acm
types_aiobotocore_acm_pca
types_aiobotocore_aiops
types_aiobotocore_amp
types_aiobotocore_amplify
types_aiobotocore_amplifybackend
types_aiobotocore_amplifyuibuilder
types_aiobotocore_apigateway
types_aiobotocore_apigatewaymanagementapi
types_aiobotocore_apigatewayv2
types_aiobotocore_appconfig
types_aiobotocore_appconfigdata
types_aiobotocore_appfabric
types_aiobotocore_appflow
types_aiobotocore_appintegrations
types_aiobotocore_application_autoscaling
types_aiobotocore_application_insights
types_aiobotocore_application_signals
types_aiobotocore_applicationcostprofiler
types_aiobotocore_appmesh
types_aiobotocore_apprunner
types_aiobotocore_appstream
types_aiobotocore_appsync
types_aiobotocore_arc_region_switch
types_aiobotocore_arc_zonal_shift
types_aiobotocore_artifact
types_aiobotocore_athena
types_aiobotocore_auditmanager
types_aiobotocore_autoscaling
types_aiobotocore_autoscaling_plans
types_aiobotocore_b2bi
types_aiobotocore_backup
types_aiobotocore_backup_gateway
types_aiobotocore_backupsearch
types_aiobotocore_batch
types_aiobotocore_bcm_dashboards
types_aiobotocore_bcm_data_exports
types_aiobotocore_bcm_pricing_calculator
types_aiobotocore_bcm_recommended_actions
types_aiobotocore_bedrock
types_aiobotocore_bedrock_agent
types_aiobotocore_bedrock_agent_runtime
types_aiobotocore_bedrock_agentcore
types_aiobotocore_bedrock_agentcore_control
types_aiobotocore_bedrock_data_automation
types_aiobotocore_bedrock_data_automation_runtime
types_aiobotocore_bedrock_runtime
types_aiobotocore_billing
types_aiobotocore_billingconductor
types_aiobotocore_braket
types_aiobotocore_budgets
types_aiobotocore_ce
types_aiobotocore_chatbot
types_aiobotocore_chime
types_aiobotocore_chime_sdk_identity
types_aiobotocore_chime_sdk_media_pipelines
types_aiobotocore_chime_sdk_meetings
types_aiobotocore_chime_sdk_messaging
types_aiobotocore_chime_sdk_voice
types_aiobotocore_cleanrooms
